rand_verify_code/__init__.py
rand_verify_code/gen_rand_verify_code.py
rand_verify_code-1.0.dist-info/METADATA
rand_verify_code-1.0.dist-info/WHEEL
rand_verify_code-1.0.dist-info/top_level.txt
rand_verify_code-1.0.dist-info/RECORD
