Metadata-Version: 2.1
Name: rand-verify-code
Version: 1.0
Summary: Generate a rand verify code!
Home-page: UNKNOWN
Author: MINGYANG LIU
Author-email: apple.liumingyang@icloud.com
License: UNKNOWN
Platform: UNKNOWN
